aws_iot_tunnel/__init__.py
aws_iot_tunnel/aws_iot_tunnel.py
aws_iot_tunnel-0.9.dist-info/METADATA
aws_iot_tunnel-0.9.dist-info/WHEEL
aws_iot_tunnel-0.9.dist-info/entry_points.txt
aws_iot_tunnel-0.9.dist-info/top_level.txt
aws_iot_tunnel-0.9.dist-info/RECORD
