Metadata-Version: 2.1
Name: aws-iot-tunnel
Version: 0.9
Summary: A script to set up and manage a secure tunnel to an AWS IoT device
Author-email: Saurabh Jarial <saurabh.jarial@smartdings.com>
Project-URL: Homepage, https://github.com/smartdings/aws-development-tools
Classifier: Programming Language :: Python :: 3
Classifier: License :: OSI Approved :: Apache Software License
Classifier: Operating System :: OS Independent
Requires-Python: >=3.6
Requires-Dist: boto3>=1.20.0
Requires-Dist: docker>=4.0.0
